skelt/__init__.py
skelt/core.py
skelt/temp.py
skelt-1.0.2.dist-info/DESCRIPTION.rst
skelt-1.0.2.dist-info/METADATA
skelt-1.0.2.dist-info/metadata.json
skelt-1.0.2.dist-info/RECORD
skelt-1.0.2.dist-info/top_level.txt
skelt-1.0.2.dist-info/WHEEL
