Metadata-Version: 2.0
Name: skelt
Version: 1.0.2
Summary: Creating and rehydrating code skeletons since 2014
Home-page: https://github.com/jklukas/skelt
Author: Jeff Klukas
Author-email: jeff@klukas.net
License: MIT
Keywords: library setup generator skeleton
Platform: UNKNOWN
Classifier: Development Status :: 4 - Beta
Classifier: Intended Audience :: Developers
Classifier: Topic :: Software Development :: Code Generators
Classifier: License :: OSI Approved :: MIT License
Classifier: Programming Language :: Python :: 3
Classifier: Programming Language :: Python :: 3.4
